myrrh/extensions/mregistry.py
myrrh/exts/__init__.py
myrrh/exts/client.py
myrrh/exts/errors.py
myrrh/exts/interfaces.py
myrrh/exts/misc.py
myrrh/exts/protocol.py
myrrh/exts/registry.py
myrrh/tools/mexts.py
myrrh_exts-0.2.1.dist-info/AUTHORS.md
myrrh_exts-0.2.1.dist-info/LICENSE
myrrh_exts-0.2.1.dist-info/METADATA
myrrh_exts-0.2.1.dist-info/WHEEL
myrrh_exts-0.2.1.dist-info/entry_points.txt
myrrh_exts-0.2.1.dist-info/top_level.txt
myrrh_exts-0.2.1.dist-info/RECORD
