Metadata-Version: 2.1
Name: myrrh-exts
Version: 0.2.1
Summary: extension manager for the myrrh project
Author-email: PyAnjel7 <pyanjel7@gmail.com>
License: GNU GENERAL PUBLIC LICENSE
Project-URL: Source, https://github.com/pyanjel7/myrrh_exts
Classifier: Development Status :: 2 - Pre-Alpha
Classifier: Operating System :: Microsoft :: Windows
Classifier: Operating System :: POSIX
Classifier: Programming Language :: Python :: 3.11
Classifier: License :: OSI Approved :: GNU General Public License v3 or later (GPLv3+)
Classifier: Intended Audience :: Developers
Classifier: Topic :: Software Development :: Libraries :: Python Modules
Classifier: Topic :: System :: Distributed Computing
Classifier: Topic :: System :: Networking
Requires-Python: >=3.11.0
License-File: LICENSE
License-File: AUTHORS.md
